{
  "enhancedWeatherDescription": "Light rain showers and light winds",
  "gustSpeedKph": 14,
  "gustSpeedMph": 9,
  "localDate": "2023-08-23",
  "lowermaxTemperatureC": null,
  "lowermaxTemperatureF": null,
  "lowerminTemperatureC": null,
  "lowerminTemperatureF": null,
  "maxTempC": 22,
  "maxTempF": 71,
  "minTempC": 16,
  "minTempF": 60,
  "mostLikelyHighTemperatureC": 24,
  "mostLikelyHighTemperatureF": 75,
  "mostLikelyLowTemperatureC": 15,
  "mostLikelyLowTemperatureF": 59,
  "pollenIndex": 6,
  "pollenIndexBand": "HIGH",
  "pollenIndexIconText": "H",
  "pollenIndexText": "High",
  "pollutionIndex": 3,
  "pollutionIndexBand": "LOW",
  "pollutionIndexIconText": "L",
  "pollutionIndexText": "Low",
  "precipitationProbabilityInPercent": 52,
  "precipitationProbabilityText": "Chance of precipitation",
  "sunrise": "06:07",
  "sunset": "20:13",
  "uppermaxTemperatureC": null,
  "uppermaxTemperatureF": null,
  "upperminTemperatureC": null,
  "upperminTemperatureF": null,
  "uvIndex": 0,
  "uvIndexBand": "LOW",
  "uvIndexIconText": "L",
  "uvIndexText": "Low",
  "weatherType": 9,
  "weatherTypeText": "Light Rain Showers",
  "windDescription": "Light winds from the north",
  "windDirection": "N",
  "windDirectionAbbreviation": "N",
  "windDirectionFull": "Northerly",
  "windSpeedKph": 9,
  "windSpeedMph": 6
}