{
  "enhancedWeatherDescription": "Light rain and a moderate breeze",
  "gustSpeedKph": 33,
  "gustSpeedMph": 21,
  "localDate": "2023-08-26",
  "lowermaxTemperatureC": null,
  "lowermaxTemperatureF": null,
  "lowerminTemperatureC": null,
  "lowerminTemperatureF": null,
  "maxTempC": 19,
  "maxTempF": 67,
  "minTempC": 11,
  "minTempF": 52,
  "mostLikelyHighTemperatureC": 20,
  "mostLikelyHighTemperatureF": 69,
  "mostLikelyLowTemperatureC": 10,
  "mostLikelyLowTemperatureF": 49,
  "pollenIndex": 6,
  "pollenIndexBand": "HIGH",
  "pollenIndexIconText": "H",
  "pollenIndexText": "High",
  "pollutionIndex": 3,
  "pollutionIndexBand": "LOW",
  "pollutionIndexIconText": "L",
  "pollutionIndexText": "Low",
  "precipitationProbabilityInPercent": 46,
  "precipitationProbabilityText": "Chance of precipitation",
  "sunrise": "06:12",
  "sunset": "20:07",
  "uppermaxTemperatureC": null,
  "uppermaxTemperatureF": null,
  "upperminTemperatureC": null,
  "upperminTemperatureF": null,
  "uvIndex": 5,
  "uvIndexBand": "MODERATE",
  "uvIndexIconText": "M",
  "uvIndexText": "Moderate",
  "weatherType": 12,
  "weatherTypeText": "Light Rain",
  "windDescription": "A moderate breeze from the west",
  "windDirection": "W",
  "windDirectionAbbreviation": "W",
  "windDirectionFull": "Westerly",
  "windSpeedKph": 22,
  "windSpeedMph": 14
}