{
  "enhancedWeatherDescription": "Sunny intervals and a gentle breeze",
  "gustSpeedKph": 27,
  "gustSpeedMph": 17,
  "localDate": "2023-09-13",
  "lowermaxTemperatureC": null,
  "lowermaxTemperatureF": null,
  "lowerminTemperatureC": null,
  "lowerminTemperatureF": null,
  "maxTempC": 19,
  "maxTempF": 67,
  "minTempC": 13,
  "minTempF": 56,
  "mostLikelyHighTemperatureC": 20,
  "mostLikelyHighTemperatureF": 68,
  "mostLikelyLowTemperatureC": 12,
  "mostLikelyLowTemperatureF": 54,
  "pollenIndex": null,
  "pollenIndexBand": null,
  "pollenIndexIconText": null,
  "pollenIndexText": null,
  "pollutionIndex": 3,
  "pollutionIndexBand": "LOW",
  "pollutionIndexIconText": "L",
  "pollutionIndexText": "Low",
  "precipitationProbabilityInPercent": 21,
  "precipitationProbabilityText": "Low chance of precipitation",
  "sunrise": "06:40",
  "sunset": "19:27",
  "uppermaxTemperatureC": null,
  "uppermaxTemperatureF": null,
  "upperminTemperatureC": null,
  "upperminTemperatureF": null,
  "uvIndex": 4,
  "uvIndexBand": "MODERATE",
  "uvIndexIconText": "M",
  "uvIndexText": "Moderate",
  "weatherType": 3,
  "weatherTypeText": "Sunny Intervals",
  "windDescription": "A gentle breeze from the north east",
  "windDirection": "NE",
  "windDirectionAbbreviation": "NE",
  "windDirectionFull": "North Easterly",
  "windSpeedKph": 18,
  "windSpeedMph": 11
}