{
  "enhancedWeatherDescription": "Partly cloudy and light winds",
  "gustSpeedKph": 18,
  "gustSpeedMph": 11,
  "localDate": "2023-07-24",
  "lowermaxTemperatureC": null,
  "lowermaxTemperatureF": null,
  "lowerminTemperatureC": null,
  "lowerminTemperatureF": null,
  "maxTempC": 19,
  "maxTempF": 66,
  "minTempC": 12,
  "minTempF": 54,
  "mostLikelyHighTemperatureC": 20,
  "mostLikelyHighTemperatureF": 67,
  "mostLikelyLowTemperatureC": 12,
  "mostLikelyLowTemperatureF": 53,
  "pollenIndex": 1,
  "pollenIndexBand": "LOW",
  "pollenIndexIconText": "L",
  "pollenIndexText": "Low",
  "pollutionIndex": 3,
  "pollutionIndexBand": "LOW",
  "pollutionIndexIconText": "L",
  "pollutionIndexText": "Low",
  "precipitationProbabilityInPercent": 0,
  "precipitationProbabilityText": "Precipitation is not expected",
  "sunrise": "05:23",
  "sunset": "21:05",
  "uppermaxTemperatureC": null,
  "uppermaxTemperatureF": null,
  "upperminTemperatureC": null,
  "upperminTemperatureF": null,
  "uvIndex": 0,
  "uvIndexBand": "LOW",
  "uvIndexIconText": "L",
  "uvIndexText": "Low",
  "weatherType": 2,
  "weatherTypeText": "Partly Cloudy",
  "windDescription": "Light winds from the north west",
  "windDirection": "NW",
  "windDirectionAbbreviation": "NW",
  "windDirectionFull": "North Westerly",
  "windSpeedKph": 12,
  "windSpeedMph": 7
}