{
  "enhancedWeatherDescription": "Light rain showers and light winds",
  "gustSpeedKph": 18,
  "gustSpeedMph": 11,
  "localDate": "2023-08-24",
  "lowermaxTemperatureC": null,
  "lowermaxTemperatureF": null,
  "lowerminTemperatureC": null,
  "lowerminTemperatureF": null,
  "maxTempC": 21,
  "maxTempF": 70,
  "minTempC": 12,
  "minTempF": 54,
  "mostLikelyHighTemperatureC": 23,
  "mostLikelyHighTemperatureF": 73,
  "mostLikelyLowTemperatureC": 11,
  "mostLikelyLowTemperatureF": 51,
  "pollenIndex": 6,
  "pollenIndexBand": "HIGH",
  "pollenIndexIconText": "H",
  "pollenIndexText": "High",
  "pollutionIndex": 2,
  "pollutionIndexBand": "LOW",
  "pollutionIndexIconText": "L",
  "pollutionIndexText": "Low",
  "precipitationProbabilityInPercent": 44,
  "precipitationProbabilityText": "Chance of precipitation",
  "sunrise": "06:09",
  "sunset": "20:11",
  "uppermaxTemperatureC": null,
  "uppermaxTemperatureF": null,
  "upperminTemperatureC": null,
  "upperminTemperatureF": null,
  "uvIndex": 5,
  "uvIndexBand": "MODERATE",
  "uvIndexIconText": "M",
  "uvIndexText": "Moderate",
  "weatherType": 10,
  "weatherTypeText": "Light Rain Showers",
  "windDescription": "Light winds from the north",
  "windDirection": "N",
  "windDirectionAbbreviation": "N",
  "windDirectionFull": "Northerly",
  "windSpeedKph": 11,
  "windSpeedMph": 7
}