{
  "enhancedWeatherDescription": "Sunny and a gentle breeze",
  "gustSpeedKph": 16,
  "gustSpeedMph": 10,
  "localDate": "2023-09-07",
  "lowermaxTemperatureC": null,
  "lowermaxTemperatureF": null,
  "lowerminTemperatureC": null,
  "lowerminTemperatureF": null,
  "maxTempC": 24,
  "maxTempF": 75,
  "minTempC": 15,
  "minTempF": 60,
  "mostLikelyHighTemperatureC": 25,
  "mostLikelyHighTemperatureF": 77,
  "mostLikelyLowTemperatureC": 14,
  "mostLikelyLowTemperatureF": 57,
  "pollenIndex": 1,
  "pollenIndexBand": "LOW",
  "pollenIndexIconText": "L",
  "pollenIndexText": "Low",
  "pollutionIndex": 3,
  "pollutionIndexBand": "LOW",
  "pollutionIndexIconText": "L",
  "pollutionIndexText": "Low",
  "precipitationProbabilityInPercent": 0,
  "precipitationProbabilityText": "Precipitation is not expected",
  "sunrise": "06:30",
  "sunset": "19:41",
  "uppermaxTemperatureC": null,
  "uppermaxTemperatureF": null,
  "upperminTemperatureC": null,
  "upperminTemperatureF": null,
  "uvIndex": 5,
  "uvIndexBand": "MODERATE",
  "uvIndexIconText": "M",
  "uvIndexText": "Moderate",
  "weatherType": 1,
  "weatherTypeText": "Sunny",
  "windDescription": "A gentle breeze from the south east",
  "windDirection": "SE",
  "windDirectionAbbreviation": "SE",
  "windDirectionFull": "South Easterly",
  "windSpeedKph": 12,
  "windSpeedMph": 8
}