{
  "enhancedWeatherDescription": "Misty and light winds",
  "gustSpeedKph": 15,
  "gustSpeedMph": 9,
  "localDate": "2023-09-05",
  "lowermaxTemperatureC": null,
  "lowermaxTemperatureF": null,
  "lowerminTemperatureC": null,
  "lowerminTemperatureF": null,
  "maxTempC": 25,
  "maxTempF": 77,
  "minTempC": 14,
  "minTempF": 57,
  "mostLikelyHighTemperatureC": 27,
  "mostLikelyHighTemperatureF": 80,
  "mostLikelyLowTemperatureC": 12,
  "mostLikelyLowTemperatureF": 54,
  "pollenIndex": 4,
  "pollenIndexBand": "MODERATE",
  "pollenIndexIconText": "M",
  "pollenIndexText": "Moderate",
  "pollutionIndex": 3,
  "pollutionIndexBand": "LOW",
  "pollutionIndexIconText": "L",
  "pollutionIndexText": "Low",
  "precipitationProbabilityInPercent": 0,
  "precipitationProbabilityText": "Precipitation is not expected",
  "sunrise": "06:27",
  "sunset": "19:45",
  "uppermaxTemperatureC": null,
  "uppermaxTemperatureF": null,
  "upperminTemperatureC": null,
  "upperminTemperatureF": null,
  "uvIndex": 2,
  "uvIndexBand": "LOW",
  "uvIndexIconText": "L",
  "uvIndexText": "Low",
  "weatherType": 34,
  "weatherTypeText": "Mist",
  "windDescription": "Light winds from the east",
  "windDirection": "E",
  "windDirectionAbbreviation": "E",
  "windDirectionFull": "Easterly",
  "windSpeedKph": 11,
  "windSpeedMph": 7
}